model_inference/__init__.py
model_inference/Inference.py
model_inference/models/__init__.py
model_inference/models/models_list.py
model_inference-0.1.0.dist-info/METADATA
model_inference-0.1.0.dist-info/WHEEL
model_inference-0.1.0.dist-info/RECORD
