Metadata-Version: 2.1
Name: model-inference
Version: 0.1.0
Summary: 
Author: Sanjith Kumar R
Author-email: sanjithkumar986@gmail.com
Requires-Python: >=3.11,<4.0
Classifier: Programming Language :: Python :: 3
Classifier: Programming Language :: Python :: 3.11
Classifier: Programming Language :: Python :: 3.12
Classifier: Programming Language :: Python :: 3.13
Requires-Dist: identity-cluster @ file:///C:/Users/ASUS/Desktop/Phosphene.AI/identity_cluster/dist/identity_cluster-0.1.0-py3-none-any.whl
Requires-Dist: numpy (==1.26.4)
Requires-Dist: opencv-python (==4.9.0.80)
Requires-Dist: pillow (==10.2.0)
Requires-Dist: torch (==2.4.1)
Requires-Dist: torchvision (==0.19.1)
